[
  {
    "name": "Daija Willms DVM",
    "email": "Tristian63@yahoo.com",
    "password_digest": "d1cf8fd4-1d22-4f1a-900e-c87efa0a6ba7",
    "isVerified": false
  },
  {
    "name": "Kyla Maggio Sr.",
    "email": "Lilian.Rau@gmail.com",
    "password_digest": "c22c51d3-6b7a-41a8-8cbe-9c07a738389d",
    "isVerified": false
  },
  {
    "name": "Kurt Ritchie I",
    "email": "Katlyn3@gmail.com",
    "password_digest": "2559b66d-c77d-48d2-a59c-93ce64c3ab5d",
    "isVerified": true
  },
  {
    "name": "Rigoberto Morissette",
    "email": "Elias_Schowalter@gmail.com",
    "password_digest": "56e277d8-cf91-4a22-b440-5c3ff592dcb2",
    "isVerified": true
  },
  {
    "name": "Trycia Powlowski",
    "email": "Jadon.Cummerata74@gmail.com",
    "password_digest": "b715e419-7779-4668-a050-11e233e96b1e",
    "isVerified": false
  },
  {
    "name": "Dee Smith V",
    "email": "Lesley_Turcotte55@gmail.com",
    "password_digest": "3a4dba23-5a85-422f-9fcd-0e24f5b079e5",
    "isVerified": true
  },
  {
    "name": "Dr. William Hegmann",
    "email": "Christophe_Funk@yahoo.com",
    "password_digest": "2da74eb6-f26d-475f-a8f1-c9d724e53765",
    "isVerified": true
  },
  {
    "name": "Jodie Kulas",
    "email": "Easter.Kunde10@gmail.com",
    "password_digest": "4042b1e9-f2c0-4015-9bcb-c8e75093d653",
    "isVerified": true
  },
  {
    "name": "Gustave Rutherford",
    "email": "Brigitte96@gmail.com",
    "password_digest": "51d17600-55a9-4b76-ba8a-890a9cc68ed9",
    "isVerified": true
  },
  {
    "name": "Cathy Kunde II",
    "email": "Dayton38@hotmail.com",
    "password_digest": "744d1de4-c726-4fb2-a1f1-21259ba38b87",
    "isVerified": true
  },
  {
    "name": "Bart Luettgen",
    "email": "Antonia.Runolfsson@yahoo.com",
    "password_digest": "93d09994-817b-4ded-9a61-d89228d971a9",
    "isVerified": true
  },
  {
    "name": "Nils Roob",
    "email": "Adriel62@gmail.com",
    "password_digest": "f12d79c3-6f1c-4416-85f4-ed6d500edc1b",
    "isVerified": true
  },
  {
    "name": "Viola Kemmer",
    "email": "Vicente63@hotmail.com",
    "password_digest": "98167b78-99c1-4580-882c-4301b8e6e4ff",
    "isVerified": false
  },
  {
    "name": "Orie Paucek",
    "email": "Maribel19@gmail.com",
    "password_digest": "5d2c97c8-9c2a-449e-ba63-ace07f1fdb12",
    "isVerified": false
  },
  {
    "name": "Martin Daugherty III",
    "email": "Eulalia.Sawayn12@hotmail.com",
    "password_digest": "7c59b82c-dd8d-4a90-b15c-585400fc14be",
    "isVerified": true
  },
  {
    "name": "Margret Torphy DDS",
    "email": "Sienna48@yahoo.com",
    "password_digest": "5b4849e5-da03-498c-9de9-91f302bf1923",
    "isVerified": false
  },
  {
    "name": "Myrtie Eichmann",
    "email": "Kiara15@gmail.com",
    "password_digest": "49af2ea8-0c74-4d15-bc11-94485d347b35",
    "isVerified": false
  },
  {
    "name": "Billy Osinski",
    "email": "Clay25@hotmail.com",
    "password_digest": "46a44dbd-aca4-4cec-9488-20a571c99983",
    "isVerified": true
  },
  {
    "name": "Brock Hayes I",
    "email": "Jeffrey_Hauck@hotmail.com",
    "password_digest": "c6cbb770-e7a1-496a-9dd5-fa52e4cbef57",
    "isVerified": false
  },
  {
    "name": "Kristofer Kemmer",
    "email": "Josephine.Farrell@hotmail.com",
    "password_digest": "9200a88b-bfa7-4c4f-9f4b-40b4bd11bb42",
    "isVerified": true
  },
  {
    "name": "Queenie Rath",
    "email": "Brianne_Reinger@gmail.com",
    "password_digest": "344bd928-56c3-44d5-ba2b-dd3bce9c05b7",
    "isVerified": false
  },
  {
    "name": "Mireya Gibson",
    "email": "Annabelle53@hotmail.com",
    "password_digest": "73958ff5-94e5-43fe-b430-4702a0d3385a",
    "isVerified": false
  },
  {
    "name": "Adam Schmitt",
    "email": "Keshaun.Upton93@hotmail.com",
    "password_digest": "b6c5f101-8f05-46af-95e2-67a28031077f",
    "isVerified": false
  },
  {
    "name": "Ms. Delta Schinner",
    "email": "Brendan.Green@hotmail.com",
    "password_digest": "44511eb2-a227-42fa-bcbf-c59efc1fa427",
    "isVerified": true
  },
  {
    "name": "Gregorio Steuber",
    "email": "Jody_Dickinson@yahoo.com",
    "password_digest": "0f6e72a8-4ad6-42aa-8577-e6f72b48c1ee",
    "isVerified": false
  },
  {
    "name": "Bernita Fahey",
    "email": "Hannah_Hegmann@gmail.com",
    "password_digest": "c368d083-0018-499c-a316-9ad49fb1b4d5",
    "isVerified": false
  },
  {
    "name": "Ezekiel Ratke",
    "email": "Matilda32@gmail.com",
    "password_digest": "05cb6a5c-854b-4acf-a5c0-e8e670b20ea0",
    "isVerified": true
  },
  {
    "name": "Timmy Mayert",
    "email": "Frederick68@hotmail.com",
    "password_digest": "585e0512-f1be-431b-86ef-bb6a5b950f6b",
    "isVerified": true
  },
  {
    "name": "Libbie Fisher",
    "email": "Madisyn96@hotmail.com",
    "password_digest": "1975a164-68f6-443f-9b4b-1af0c69cd42c",
    "isVerified": false
  },
  {
    "name": "Lemuel Gibson",
    "email": "Horacio.Cormier3@gmail.com",
    "password_digest": "cf0b4624-d7a2-4705-b53b-b81a45b119f6",
    "isVerified": true
  },
  {
    "name": "Jackson Harvey",
    "email": "Ebony53@gmail.com",
    "password_digest": "0d77bf00-307b-4d89-9557-a556a3ef0f00",
    "isVerified": true
  },
  {
    "name": "Miss Jerel Haley",
    "email": "Blaze46@hotmail.com",
    "password_digest": "eeee6a78-c9d0-4b01-b4d2-07e4d3a69df3",
    "isVerified": false
  },
  {
    "name": "Marcelina Langosh",
    "email": "Annetta4@gmail.com",
    "password_digest": "2ca29f73-ff38-42e6-9d8d-b5f3a1f0bda9",
    "isVerified": false
  },
  {
    "name": "Dr. Cooper Hauck",
    "email": "Fatima.Hettinger8@hotmail.com",
    "password_digest": "f13d5852-a9a0-4d40-9af0-0545dbd32678",
    "isVerified": false
  },
  {
    "name": "Mrs. Elfrieda Simonis",
    "email": "Aurelio.Lesch@hotmail.com",
    "password_digest": "42c28fd8-2ca2-424c-837d-44319c2d49bc",
    "isVerified": true
  },
  {
    "name": "Thaddeus Marquardt",
    "email": "Alisa.Nienow98@hotmail.com",
    "password_digest": "d6e0a3d3-9286-4dd3-86d4-b7dec3395d3e",
    "isVerified": true
  },
  {
    "name": "Hermann Schoen",
    "email": "Charlene.Kuvalis@yahoo.com",
    "password_digest": "20506a88-7a03-47e0-83da-2507c11af04a",
    "isVerified": true
  },
  {
    "name": "Hulda Schmitt DDS",
    "email": "Toni.Miller50@gmail.com",
    "password_digest": "6f861449-882b-464f-8ba3-50ba64d95113",
    "isVerified": false
  },
  {
    "name": "Ibrahim Konopelski",
    "email": "Rubie23@hotmail.com",
    "password_digest": "5a65769c-37ba-484b-b275-9e8f6b229554",
    "isVerified": false
  },
  {
    "name": "Alaina Johnson",
    "email": "Annie56@hotmail.com",
    "password_digest": "46bc8a67-61c3-45e8-8c77-8679bc1ae257",
    "isVerified": true
  },
  {
    "name": "Janae Yundt DVM",
    "email": "Vladimir70@hotmail.com",
    "password_digest": "13b16c37-31c9-4cd7-bfa7-9a4e7f6edc46",
    "isVerified": true
  },
  {
    "name": "Pierce Carter",
    "email": "Monroe.Torphy78@hotmail.com",
    "password_digest": "7e06f7a7-f5af-4851-96a6-2e0dc912c666",
    "isVerified": true
  },
  {
    "name": "Albertha Ritchie",
    "email": "Nicklaus21@hotmail.com",
    "password_digest": "ed27250b-46ac-4354-b4c0-24a014ec9a5d",
    "isVerified": true
  },
  {
    "name": "Ms. Bryon Jenkins",
    "email": "Jenifer_Stroman@yahoo.com",
    "password_digest": "d6f5630f-b629-4471-b9be-64d315ff7fb8",
    "isVerified": true
  },
  {
    "name": "Amaya McClure",
    "email": "Blanche16@gmail.com",
    "password_digest": "11579765-76b8-4b20-b38c-b89bbab589cd",
    "isVerified": false
  },
  {
    "name": "Manuel Quigley",
    "email": "Aditya_Schaefer29@gmail.com",
    "password_digest": "b891fc44-84e1-4c24-92e5-85eda0c14bdc",
    "isVerified": true
  },
  {
    "name": "Federico Dickens",
    "email": "Yasmeen_Streich93@yahoo.com",
    "password_digest": "15cdac4e-348c-414a-b384-ac532013222a",
    "isVerified": true
  },
  {
    "name": "Zoey Weissnat",
    "email": "Katherine.Hammes40@gmail.com",
    "password_digest": "306fee14-25c9-40dd-a1d8-09ab3e79fcb8",
    "isVerified": true
  },
  {
    "name": "Mrs. Bridgette Muller",
    "email": "Kenya90@yahoo.com",
    "password_digest": "7620b658-64c8-4b57-8d4d-ca75c71ceb7c",
    "isVerified": false
  },
  {
    "name": "Tobin Kilback",
    "email": "Maynard.Kreiger77@hotmail.com",
    "password_digest": "ee1bf214-38f6-43d8-b66f-39347df6eb81",
    "isVerified": true
  },
  {
    "name": "Alvera Schulist",
    "email": "Sheldon86@gmail.com",
    "password_digest": "a55880b3-5fd1-4d38-95a0-ee056bb7cfba",
    "isVerified": true
  },
  {
    "name": "Albin Hoeger",
    "email": "Rolando.Hand64@yahoo.com",
    "password_digest": "3f6e4fd5-ab8c-46ee-aeb6-0e60f72206fa",
    "isVerified": true
  },
  {
    "name": "Brody O'Keefe",
    "email": "Dillan37@hotmail.com",
    "password_digest": "54520ac8-e4e7-4b01-862c-200a59426379",
    "isVerified": false
  },
  {
    "name": "Alexie Hyatt",
    "email": "Myrna.Swift44@gmail.com",
    "password_digest": "003ad689-2e35-4fc7-a1e3-c85d749b1638",
    "isVerified": false
  },
  {
    "name": "Columbus Conroy",
    "email": "Kevin.Franecki30@hotmail.com",
    "password_digest": "20237536-03c5-4cd0-bf04-9a494e484bca",
    "isVerified": false
  },
  {
    "name": "Adrien Stoltenberg",
    "email": "Russ56@gmail.com",
    "password_digest": "dbd77108-5ed6-4532-8da9-b6ec95efe0d1",
    "isVerified": true
  },
  {
    "name": "Darrick Waters",
    "email": "Maegan.Schoen@hotmail.com",
    "password_digest": "ca25fd91-7311-41c8-baa5-1cbc48fd1bca",
    "isVerified": true
  },
  {
    "name": "Dr. America Abbott",
    "email": "Natalia_Gleichner@gmail.com",
    "password_digest": "2306c42c-9606-4def-856d-5725a47a46a4",
    "isVerified": false
  },
  {
    "name": "Pat Feeney DDS",
    "email": "Braeden78@yahoo.com",
    "password_digest": "6902230b-c191-4e77-8ae9-458795e4ccbd",
    "isVerified": true
  },
  {
    "name": "Edwardo Mohr",
    "email": "Shanny82@hotmail.com",
    "password_digest": "0f3a1064-afaf-499b-ae66-696bacf77387",
    "isVerified": false
  },
  {
    "name": "Kristian Christiansen",
    "email": "Ezekiel17@hotmail.com",
    "password_digest": "45ecdf73-4a86-4c63-a1c7-9f9162619ce3",
    "isVerified": true
  },
  {
    "name": "Jadon Bednar",
    "email": "Vanessa35@gmail.com",
    "password_digest": "64abf593-5966-4575-b124-938ed3a11fb4",
    "isVerified": false
  },
  {
    "name": "Troy White",
    "email": "Devon_Schinner@gmail.com",
    "password_digest": "69b4f93d-cd92-4d9e-9e8c-9eaee00d6ff4",
    "isVerified": false
  },
  {
    "name": "Lillie Hilll",
    "email": "Quentin.Stokes@yahoo.com",
    "password_digest": "436afb80-3d9e-459f-8367-a2fa1643e442",
    "isVerified": false
  },
  {
    "name": "Theresia Terry",
    "email": "Tiara.Doyle@gmail.com",
    "password_digest": "bab682fd-56a6-4269-a414-4b1d99e56702",
    "isVerified": true
  },
  {
    "name": "Mrs. Gabriel Kohler",
    "email": "Gaetano_Kub@gmail.com",
    "password_digest": "57e5c15c-d672-4c6c-ae74-e6a2bf247105",
    "isVerified": true
  },
  {
    "name": "Trenton Gusikowski",
    "email": "Davonte6@hotmail.com",
    "password_digest": "956ae66a-fa5a-4153-9225-d3bee227df84",
    "isVerified": false
  },
  {
    "name": "Sheila Gleason I",
    "email": "Laurel60@yahoo.com",
    "password_digest": "19528f57-f1ad-4dd9-aa41-5e84f4c5ae29",
    "isVerified": false
  },
  {
    "name": "Gunnar Becker",
    "email": "Zackary.Johns1@yahoo.com",
    "password_digest": "e801ba86-84cd-4b36-9fc3-70f41b914dc7",
    "isVerified": false
  },
  {
    "name": "Shanna Zieme",
    "email": "Jules_Kutch@yahoo.com",
    "password_digest": "f91ad6ea-f3f4-4b3e-a1b8-045454ceab47",
    "isVerified": true
  },
  {
    "name": "Jesse Williamson",
    "email": "Gregorio89@yahoo.com",
    "password_digest": "a02d4201-9f28-411f-921d-ad3f45176542",
    "isVerified": false
  },
  {
    "name": "Myron Wiegand",
    "email": "Maximillia_Zieme@gmail.com",
    "password_digest": "90058fa5-c1a4-41e7-a48c-d20cfc6d28d5",
    "isVerified": true
  },
  {
    "name": "Leonardo Dickinson",
    "email": "Ryder.Waters@gmail.com",
    "password_digest": "6bcf9a20-2a79-4779-b3cd-efdc7c46af55",
    "isVerified": true
  },
  {
    "name": "Arlie Abbott",
    "email": "Teagan66@yahoo.com",
    "password_digest": "d566eb62-d74d-4024-85d8-33dd14b370ff",
    "isVerified": true
  },
  {
    "name": "Jeanette Feil",
    "email": "Ashlee15@gmail.com",
    "password_digest": "074150ae-685b-47a3-bf9f-977992cb8005",
    "isVerified": true
  },
  {
    "name": "Chase Mann",
    "email": "Lesly76@hotmail.com",
    "password_digest": "75c38cc5-4abe-4bef-80c9-ce7e191a252f",
    "isVerified": true
  },
  {
    "name": "Icie Gibson",
    "email": "Florian_Haag95@yahoo.com",
    "password_digest": "b006dd88-7ded-4059-924c-e294e6dfdc6a",
    "isVerified": false
  },
  {
    "name": "Ima Ernser",
    "email": "Alia93@yahoo.com",
    "password_digest": "daa58b20-5e56-43d6-8312-1b43173e2c9a",
    "isVerified": true
  },
  {
    "name": "Einar Becker",
    "email": "Georgiana.Parker@yahoo.com",
    "password_digest": "cb0bcc1f-1a6a-4cce-a352-78e0a151719e",
    "isVerified": false
  },
  {
    "name": "Pansy Heaney",
    "email": "Rebeca.Ruecker@hotmail.com",
    "password_digest": "32a31319-7502-4d01-9d08-54e45900c067",
    "isVerified": true
  },
  {
    "name": "Verdie O'Hara",
    "email": "Vada_Reilly@gmail.com",
    "password_digest": "7b1ffad6-11a4-4f7f-971a-2324763cfcf5",
    "isVerified": false
  },
  {
    "name": "Karson Adams",
    "email": "Wilmer_Paucek@gmail.com",
    "password_digest": "2fb1c911-4198-4eac-8320-6aacac6cd447",
    "isVerified": false
  },
  {
    "name": "Eriberto Strosin",
    "email": "Kaylin98@hotmail.com",
    "password_digest": "fe7401d8-37cc-47e4-ad02-ca1e9cad5c57",
    "isVerified": false
  },
  {
    "name": "Easton Kihn",
    "email": "Garnett.Konopelski@hotmail.com",
    "password_digest": "a5063ea8-bc77-4616-9d0a-dd3dc575e09b",
    "isVerified": false
  },
  {
    "name": "Adalberto Gutmann",
    "email": "Anna.Ankunding@hotmail.com",
    "password_digest": "16c9b3c2-8d20-46bc-8250-699bf41cc4d8",
    "isVerified": false
  },
  {
    "name": "Clyde D'Amore",
    "email": "Josiah_Wehner79@yahoo.com",
    "password_digest": "bc60b2bd-1336-4a70-ad4a-65b929a115d1",
    "isVerified": true
  },
  {
    "name": "Stanford Greenholt",
    "email": "Madilyn20@gmail.com",
    "password_digest": "cb841eab-8ec8-452f-b94d-80aa27b27110",
    "isVerified": true
  },
  {
    "name": "Carli Smitham",
    "email": "Susie0@hotmail.com",
    "password_digest": "28d5ad24-e0eb-4845-a51f-c301376b5982",
    "isVerified": true
  },
  {
    "name": "Guiseppe Cole Jr.",
    "email": "Annalise98@gmail.com",
    "password_digest": "e9726c3e-6325-434a-aa82-b52f07230cd4",
    "isVerified": true
  },
  {
    "name": "Percival Cremin",
    "email": "Elmore.Raynor23@hotmail.com",
    "password_digest": "5a7a36ec-ffb0-4015-a347-bc7ff69097a6",
    "isVerified": true
  },
  {
    "name": "Tabitha Wintheiser",
    "email": "Arnold97@hotmail.com",
    "password_digest": "ea10effe-a797-4e63-afde-ab63741a6daa",
    "isVerified": false
  },
  {
    "name": "Ms. Barton Towne",
    "email": "Marlee83@hotmail.com",
    "password_digest": "9ea4cafc-865f-494e-87eb-24eb778aabe8",
    "isVerified": false
  },
  {
    "name": "Reece Bradtke",
    "email": "Iliana.Jones@yahoo.com",
    "password_digest": "4e4beeb5-8466-43e0-9d32-64a0b121d864",
    "isVerified": false
  },
  {
    "name": "Helmer Heller",
    "email": "Leila17@gmail.com",
    "password_digest": "ae333d9a-4b1c-4bf7-a0f8-d0f8787daca7",
    "isVerified": true
  },
  {
    "name": "Oceane McKenzie",
    "email": "Danyka_Gerhold@yahoo.com",
    "password_digest": "24d58d52-a85e-485e-8783-59d462684c59",
    "isVerified": true
  },
  {
    "name": "Alfredo Kreiger",
    "email": "Queenie.Kiehn@gmail.com",
    "password_digest": "f377ed7b-91dc-48da-ba43-1ea50b7317a7",
    "isVerified": false
  },
  {
    "name": "Susana Deckow",
    "email": "Giovani_Sanford96@yahoo.com",
    "password_digest": "49a0b5e5-d335-48a3-be35-09fb4d11129d",
    "isVerified": false
  },
  {
    "name": "Leilani Gulgowski",
    "email": "Dane32@hotmail.com",
    "password_digest": "f68cd171-5822-4163-b3c4-82279fc047e6",
    "isVerified": false
  },
  {
    "name": "Talon Beier",
    "email": "Mavis_McLaughlin@yahoo.com",
    "password_digest": "de4ac28a-d03e-4dcb-84c8-c39606ae4c4b",
    "isVerified": true
  },
  {
    "name": "Lorenzo Sipes",
    "email": "Augustus_Schowalter1@yahoo.com",
    "password_digest": "3d03fc0a-1567-4b57-84d1-d624b88e801c",
    "isVerified": false
  },
  {
    "name": "Eric Kautzer",
    "email": "Melvin_Schmeler@yahoo.com",
    "password_digest": "1e41ce5e-e317-4177-86fe-a34ec8052168",
    "isVerified": false
  },
  {
    "name": "Russel Abshire",
    "email": "Madaline0@yahoo.com",
    "password_digest": "3d94c31d-bd91-422d-83f6-0dd1c4c7c827",
    "isVerified": false
  },
  {
    "name": "Agustin Stanton",
    "email": "Juanita.Pagac50@hotmail.com",
    "password_digest": "f384518a-c44a-4c0e-b835-605206fc4f6c",
    "isVerified": true
  },
  {
    "name": "Alfreda Monahan",
    "email": "Kelli.Fay@hotmail.com",
    "password_digest": "4ac44c0b-71e6-40b2-9a93-41ab15fc5f8e",
    "isVerified": false
  },
  {
    "name": "Maxime Hickle",
    "email": "Ewell.Skiles@gmail.com",
    "password_digest": "cf8e8e5f-1668-4583-af09-c8fae5166b8b",
    "isVerified": true
  },
  {
    "name": "Gillian Ward",
    "email": "Leif.Welch@yahoo.com",
    "password_digest": "88922813-d84a-4c93-9133-4a9c384ce905",
    "isVerified": false
  },
  {
    "name": "Nash Schuppe",
    "email": "Ignatius23@gmail.com",
    "password_digest": "c947bf0f-d19d-4db7-b60f-cbe96c658e09",
    "isVerified": false
  },
  {
    "name": "Alec Bernier",
    "email": "Lina_Schumm37@yahoo.com",
    "password_digest": "3c46a7a7-a606-43c1-92fb-336076b5fa4c",
    "isVerified": true
  },
  {
    "name": "Viola Kuphal",
    "email": "Gage.Grimes12@hotmail.com",
    "password_digest": "e2e4e9ee-a6dc-47ad-8f1c-6dbf3497f34c",
    "isVerified": false
  },
  {
    "name": "Marianna Zieme I",
    "email": "David_Weissnat61@yahoo.com",
    "password_digest": "aa090d8c-2bef-4193-b619-fca36105a07a",
    "isVerified": false
  },
  {
    "name": "Tobin Blanda",
    "email": "Wilton40@yahoo.com",
    "password_digest": "94d0b247-2d2d-4a26-b5f5-1d1e0d0401eb",
    "isVerified": false
  },
  {
    "name": "Ettie Witting",
    "email": "Rahsaan.Mueller@yahoo.com",
    "password_digest": "2d3ec31b-d200-4265-9a6b-b8ecc99886af",
    "isVerified": false
  },
  {
    "name": "Mr. Michale Hilll",
    "email": "Vernon.Rodriguez84@gmail.com",
    "password_digest": "103bd72d-0767-4bb3-889c-b1819c042a39",
    "isVerified": true
  },
  {
    "name": "Summer Lowe",
    "email": "Rocky.Walter@yahoo.com",
    "password_digest": "39907026-61dc-4e56-8627-6004bb431c35",
    "isVerified": true
  },
  {
    "name": "Americo Reichel I",
    "email": "Mireya84@gmail.com",
    "password_digest": "3d044392-2a71-43b2-8b3c-46ebfaa0e822",
    "isVerified": true
  },
  {
    "name": "Marques Blanda",
    "email": "Jimmie.Hackett@gmail.com",
    "password_digest": "a5ee466e-89d9-4649-b7f0-a2a73ca30389",
    "isVerified": true
  },
  {
    "name": "Gloria Streich",
    "email": "Herbert_Gislason36@hotmail.com",
    "password_digest": "12ad2775-7754-41f9-b6f5-2709e89a15d2",
    "isVerified": false
  },
  {
    "name": "Mason Schaefer",
    "email": "Delta45@hotmail.com",
    "password_digest": "0c54e201-1bb4-4086-b0f9-b221a3a0af4b",
    "isVerified": true
  },
  {
    "name": "Mervin Kuphal",
    "email": "Trace_Ernser@hotmail.com",
    "password_digest": "7e929521-444c-4f09-b5ac-8163ef0c9abf",
    "isVerified": true
  },
  {
    "name": "Keagan Leannon II",
    "email": "Jeanne91@hotmail.com",
    "password_digest": "09e9d6dd-4986-44b0-a4a3-524ba85255d8",
    "isVerified": true
  },
  {
    "name": "Willow Rosenbaum",
    "email": "Karlee20@hotmail.com",
    "password_digest": "8e79ea71-4cff-49a7-9de4-c0bfa8fcd03b",
    "isVerified": true
  },
  {
    "name": "Leora Osinski",
    "email": "Madaline.Treutel4@gmail.com",
    "password_digest": "6f4fb0b7-5d26-4308-b9c8-20bb95bdd57b",
    "isVerified": false
  },
  {
    "name": "Osbaldo Welch",
    "email": "Mariane_Heller42@gmail.com",
    "password_digest": "48e98e34-d328-4c3a-abc0-d01af9b4997f",
    "isVerified": true
  },
  {
    "name": "Ms. Domenic Smitham",
    "email": "Makenzie66@gmail.com",
    "password_digest": "52e71e31-bf33-4ca4-88ac-283f365053e6",
    "isVerified": true
  },
  {
    "name": "Kareem Schuppe",
    "email": "Alice88@yahoo.com",
    "password_digest": "c3ca5b8e-7cf0-478d-b827-d35eb0f65d0e",
    "isVerified": false
  },
  {
    "name": "Laron Altenwerth",
    "email": "Consuelo.Luettgen79@yahoo.com",
    "password_digest": "ac5142f1-1ba9-4086-94d4-e5293a38dd36",
    "isVerified": true
  },
  {
    "name": "Laisha Harvey",
    "email": "Helene73@gmail.com",
    "password_digest": "8df51639-29ed-4a5c-b105-c9794d0252f6",
    "isVerified": false
  },
  {
    "name": "Mariano Kirlin",
    "email": "Leland65@yahoo.com",
    "password_digest": "a8e2a5c8-d62d-44ed-a645-26c56f8bc9e8",
    "isVerified": true
  },
  {
    "name": "Bridie Conroy",
    "email": "Alta23@hotmail.com",
    "password_digest": "10bf53de-b3e4-480a-a67b-9c7b2102fce3",
    "isVerified": false
  },
  {
    "name": "Meda Bechtelar",
    "email": "Lonnie_Jerde50@gmail.com",
    "password_digest": "efd482e0-3040-4ccb-86e5-03357d97e92e",
    "isVerified": true
  },
  {
    "name": "Cody Johnston",
    "email": "Creola_Blick50@hotmail.com",
    "password_digest": "7fc0eda9-37e2-41b9-bee0-55f59f9cb634",
    "isVerified": false
  },
  {
    "name": "Brenna Stracke",
    "email": "Lora.Brekke70@hotmail.com",
    "password_digest": "6147cc6b-15a7-4bcb-ad3d-5a7497da2352",
    "isVerified": false
  },
  {
    "name": "Jonathon Macejkovic",
    "email": "Kara.Brown@yahoo.com",
    "password_digest": "86b647fd-b991-4ec1-ba2e-aeedd4f35872",
    "isVerified": false
  },
  {
    "name": "Anahi Welch",
    "email": "Carmella70@hotmail.com",
    "password_digest": "44adcf27-430a-4f65-8e35-6c386acada15",
    "isVerified": true
  },
  {
    "name": "Retta Schimmel",
    "email": "Eloisa.Price78@hotmail.com",
    "password_digest": "0b9b8c03-46f1-43dd-8f11-e0f2d35bb6ac",
    "isVerified": false
  },
  {
    "name": "Brooklyn Kshlerin",
    "email": "Kathleen59@yahoo.com",
    "password_digest": "a485f095-84f3-4a95-a9f5-11ed05e287b0",
    "isVerified": true
  },
  {
    "name": "Savion Ankunding",
    "email": "Sonia8@hotmail.com",
    "password_digest": "a3e4a390-1bc9-4acb-9a0e-3638fb59f677",
    "isVerified": true
  },
  {
    "name": "Giovanna Carter IV",
    "email": "Rogers_Schoen@gmail.com",
    "password_digest": "654cca7c-a084-434c-a626-162bdf8d4b06",
    "isVerified": true
  },
  {
    "name": "Lyla Willms",
    "email": "Jonathon50@hotmail.com",
    "password_digest": "f6dfb667-cf63-4012-8b8d-b65313be5727",
    "isVerified": true
  },
  {
    "name": "Carli Rolfson",
    "email": "Delfina_Turcotte@yahoo.com",
    "password_digest": "e4a93d72-e906-40cf-9e7f-f9fbb12b5ada",
    "isVerified": true
  },
  {
    "name": "Kian Dickens",
    "email": "Erwin.Fahey@gmail.com",
    "password_digest": "b9712db9-7551-4f17-9070-f2a66fd40789",
    "isVerified": false
  },
  {
    "name": "Miss Tatyana Stamm",
    "email": "Furman.Runte@hotmail.com",
    "password_digest": "743ed6eb-c7f9-4011-9cdb-189673b73ac9",
    "isVerified": false
  },
  {
    "name": "Mr. Cyrus Bartoletti",
    "email": "Marcelino.Turner35@hotmail.com",
    "password_digest": "3fa342e7-791c-45cb-9122-c9ac11945988",
    "isVerified": true
  },
  {
    "name": "Milford Ankunding DVM",
    "email": "Nellie5@yahoo.com",
    "password_digest": "b095f6c3-598f-416d-8885-ec193e17a6b3",
    "isVerified": true
  },
  {
    "name": "Maria McKenzie",
    "email": "Anabelle_Wehner77@gmail.com",
    "password_digest": "336177b5-e867-42ef-b06e-2387d8ad5fe6",
    "isVerified": false
  },
  {
    "name": "Shanie Kunde",
    "email": "Laurel_Farrell@gmail.com",
    "password_digest": "219a7f80-81cd-444c-8a1a-1f01099fd244",
    "isVerified": true
  },
  {
    "name": "Dortha Bauch",
    "email": "Mireille_Heathcote72@gmail.com",
    "password_digest": "ad051cc6-21d9-4d1b-a183-39496dede320",
    "isVerified": true
  },
  {
    "name": "Twila Jacobs",
    "email": "Lucinda78@hotmail.com",
    "password_digest": "e2fd3a72-f6e3-49b7-8e82-7ebc07ab3c67",
    "isVerified": false
  },
  {
    "name": "Hassie Pacocha",
    "email": "Savannah.Stanton7@yahoo.com",
    "password_digest": "3410c871-4cf2-43f2-b521-11152a9a5b28",
    "isVerified": false
  },
  {
    "name": "Carmen Mann",
    "email": "Josianne.Hamill@hotmail.com",
    "password_digest": "5127cf9f-b0a3-4e31-9e93-52289c5ed493",
    "isVerified": true
  },
  {
    "name": "Maryse Streich",
    "email": "Ross.Waters14@yahoo.com",
    "password_digest": "ba9ec0a3-2ca2-4b3e-a648-b8840f861b00",
    "isVerified": false
  },
  {
    "name": "Mr. Crawford Homenick",
    "email": "Cassie46@yahoo.com",
    "password_digest": "8f1aecc2-fad6-477a-aa47-4d5c72cdcc4e",
    "isVerified": false
  },
  {
    "name": "Natalia Bahringer",
    "email": "Michaela_Langworth21@gmail.com",
    "password_digest": "649ec07f-3e80-4b04-b329-da351214a999",
    "isVerified": true
  },
  {
    "name": "Adolf Nitzsche",
    "email": "Katrina.Robel51@yahoo.com",
    "password_digest": "a2428697-1933-44d9-bde6-d7ae75fc2374",
    "isVerified": false
  },
  {
    "name": "Melyna Witting",
    "email": "Aimee18@yahoo.com",
    "password_digest": "579a76f4-07e0-4747-aadc-0868d1e0835c",
    "isVerified": true
  },
  {
    "name": "Mr. Reagan Schuppe",
    "email": "Daren_Durgan@yahoo.com",
    "password_digest": "7f497f09-88d4-4b0a-9dfa-3a1df5b6f36d",
    "isVerified": true
  },
  {
    "name": "Miss Francisco Hills",
    "email": "Miracle_Hintz94@hotmail.com",
    "password_digest": "1a17c698-4cb7-40fe-bd7d-591253c4c0fe",
    "isVerified": true
  },
  {
    "name": "Reinhold Huels",
    "email": "Hollie19@hotmail.com",
    "password_digest": "f5d2ec34-7ec6-402d-b4a5-17c811a8ba22",
    "isVerified": false
  },
  {
    "name": "Mrs. Juanita Nitzsche",
    "email": "Luna7@yahoo.com",
    "password_digest": "e8bd4469-fff1-4b06-bbbb-7b9426ae6195",
    "isVerified": false
  },
  {
    "name": "Freeda West",
    "email": "Ferne_Johnston83@gmail.com",
    "password_digest": "c9670803-3bde-4e0a-b3c8-0e84bfc68435",
    "isVerified": false
  },
  {
    "name": "Carli Weimann",
    "email": "Jeramy_Kirlin@yahoo.com",
    "password_digest": "01da9264-d5c9-4526-97a2-a9d5363b13e2",
    "isVerified": true
  },
  {
    "name": "Lilian Koelpin",
    "email": "Juana_Fadel87@gmail.com",
    "password_digest": "5fe7c4cb-efed-4a89-9e09-0087e3f0411c",
    "isVerified": false
  },
  {
    "name": "Brice Rutherford",
    "email": "Candace37@yahoo.com",
    "password_digest": "9dfab517-aebf-4d16-8c4c-dab8b0bce8ed",
    "isVerified": true
  },
  {
    "name": "Emerson Fisher",
    "email": "Kole18@hotmail.com",
    "password_digest": "55dab4ab-52b8-4e1f-9759-0af94b78ec9c",
    "isVerified": false
  },
  {
    "name": "Sonny Hackett",
    "email": "Lee10@gmail.com",
    "password_digest": "71c33c41-133c-489a-bbde-1f1c16865529",
    "isVerified": false
  },
  {
    "name": "Amaya Haag",
    "email": "Domenico16@gmail.com",
    "password_digest": "1c1bea6c-707b-41f7-9d75-8e60d3d42b28",
    "isVerified": false
  },
  {
    "name": "Mittie Torp",
    "email": "Garrison.Runolfsson@gmail.com",
    "password_digest": "6b95a2a7-01bd-4a3c-a797-498736a27653",
    "isVerified": true
  },
  {
    "name": "Elyse Zulauf",
    "email": "Lazaro.Leuschke@hotmail.com",
    "password_digest": "aebe8ef9-32a8-4bd3-9ebe-a269e92b18dd",
    "isVerified": true
  },
  {
    "name": "Miss Josue Lowe",
    "email": "Timothy.Koepp70@gmail.com",
    "password_digest": "a177f098-c680-48c7-a883-041d1a5145a7",
    "isVerified": false
  },
  {
    "name": "Breana Little MD",
    "email": "Tre51@hotmail.com",
    "password_digest": "4f170f3f-be20-478d-9337-f2d77c81f65a",
    "isVerified": false
  },
  {
    "name": "Christa Bogisich",
    "email": "Royce_Lindgren@hotmail.com",
    "password_digest": "f894ada6-f33c-48b3-ad16-553f9670f051",
    "isVerified": false
  },
  {
    "name": "Layla Rodriguez",
    "email": "Monserrate30@yahoo.com",
    "password_digest": "1d5b321a-621b-4ae6-98ac-ff568d8a3609",
    "isVerified": false
  },
  {
    "name": "Aisha Senger",
    "email": "Cleora_Mertz79@gmail.com",
    "password_digest": "04785f2a-3ee9-4518-8746-8973dca837e4",
    "isVerified": true
  },
  {
    "name": "Alvera Towne",
    "email": "Angelo.Yost@yahoo.com",
    "password_digest": "9a3107bb-4aee-4ce9-bfc7-eed84e0bd9ea",
    "isVerified": false
  },
  {
    "name": "Tabitha Schinner",
    "email": "Juanita_Borer10@hotmail.com",
    "password_digest": "4def3d2c-d1cc-4b0f-82b7-92e315e9df55",
    "isVerified": true
  },
  {
    "name": "Garrett McClure",
    "email": "Rosa_Blick@hotmail.com",
    "password_digest": "1b579f9f-5729-429b-b06e-baac4e83414c",
    "isVerified": true
  },
  {
    "name": "Brett Doyle",
    "email": "Kaelyn83@gmail.com",
    "password_digest": "1ac70323-6e94-4126-ba1b-59bba5c3cb3c",
    "isVerified": true
  },
  {
    "name": "Lesley Lesch",
    "email": "Ivory.Kuhlman10@hotmail.com",
    "password_digest": "3275eebb-e2de-4ea1-86c9-6a9deda468c6",
    "isVerified": true
  },
  {
    "name": "Zackary Jacobson",
    "email": "Celia57@yahoo.com",
    "password_digest": "61dd3800-7494-472f-8d64-2ce2b1a09993",
    "isVerified": false
  },
  {
    "name": "Heloise Schowalter",
    "email": "Garnett_Witting75@hotmail.com",
    "password_digest": "0f3a877e-ea16-48bc-a4e9-a80cc3cb4d31",
    "isVerified": true
  },
  {
    "name": "Grace Thompson",
    "email": "Mafalda_Johnson@yahoo.com",
    "password_digest": "8598078b-b1e5-4ee8-895c-1b6e82767b1e",
    "isVerified": true
  },
  {
    "name": "Jarrell Hills",
    "email": "Delia94@gmail.com",
    "password_digest": "493b91d3-f66c-4d42-bad4-9d5f279dfd0f",
    "isVerified": false
  },
  {
    "name": "Enos Lueilwitz Sr.",
    "email": "Abelardo.Ledner@gmail.com",
    "password_digest": "9f778f0f-2a31-4e7d-a230-cdd3e8b837e3",
    "isVerified": false
  },
  {
    "name": "Ernesto VonRueden",
    "email": "Foster_Farrell@hotmail.com",
    "password_digest": "27dc1038-b71c-4ea2-9a9d-06ff259435d6",
    "isVerified": true
  },
  {
    "name": "Tyrell Quitzon",
    "email": "Devin15@yahoo.com",
    "password_digest": "efcd4b8f-3e64-495e-8959-f4a954073613",
    "isVerified": true
  },
  {
    "name": "Miss Deanna Medhurst",
    "email": "Chelsie.Feest68@yahoo.com",
    "password_digest": "b72129fa-6348-4f03-81b1-dece9abc4365",
    "isVerified": true
  },
  {
    "name": "Antwon Schaden",
    "email": "Kaya_Lowe14@yahoo.com",
    "password_digest": "8440290c-c780-4132-b5b3-c59b9aedfa00",
    "isVerified": true
  },
  {
    "name": "Devan Bayer",
    "email": "Kaela_Romaguera@hotmail.com",
    "password_digest": "2178d8c4-d5e2-4df6-9ee4-c837ee6eddf9",
    "isVerified": true
  },
  {
    "name": "Nolan Leuschke",
    "email": "Thad_Rau@hotmail.com",
    "password_digest": "d1c2b51b-8618-4f2e-8918-5330bba2bd5c",
    "isVerified": true
  },
  {
    "name": "Amber Barrows Jr.",
    "email": "Jany93@hotmail.com",
    "password_digest": "5b70bc7c-d6b4-4f03-b449-9c7ea094bea3",
    "isVerified": true
  },
  {
    "name": "Edyth Spencer",
    "email": "Mariane.Hagenes@gmail.com",
    "password_digest": "6c7c0303-4d15-4766-b962-7580d6be9b3b",
    "isVerified": false
  },
  {
    "name": "Martine Boyle MD",
    "email": "Stephon_Glover85@gmail.com",
    "password_digest": "9de1af07-829d-4597-8530-4b2843b76554",
    "isVerified": false
  },
  {
    "name": "Desmond Wolff",
    "email": "Levi.Strosin@yahoo.com",
    "password_digest": "d021ec37-7c0a-4888-b3cb-0e0816395f5a",
    "isVerified": true
  },
  {
    "name": "Vada Rutherford",
    "email": "Sadie.Kuhn@hotmail.com",
    "password_digest": "73b5166d-f084-46eb-809b-79122910062b",
    "isVerified": true
  },
  {
    "name": "Valentin Kautzer",
    "email": "Peter_Graham10@yahoo.com",
    "password_digest": "cf048a87-af24-420d-816c-0bedb67eb959",
    "isVerified": false
  },
  {
    "name": "Gina Goyette",
    "email": "Darrel_Jacobs15@hotmail.com",
    "password_digest": "af8e5b48-68e8-46f1-9302-d0efd1762eb5",
    "isVerified": false
  },
  {
    "name": "Myles Halvorson",
    "email": "Bette11@gmail.com",
    "password_digest": "c5520b9d-85bd-4991-b6b0-3579e9069fd2",
    "isVerified": false
  },
  {
    "name": "Chelsey Bosco",
    "email": "Valentine_Legros80@gmail.com",
    "password_digest": "4078fd8e-59fc-40b7-8e03-2817c0bf4cb0",
    "isVerified": false
  },
  {
    "name": "Breana Kertzmann",
    "email": "Fidel94@yahoo.com",
    "password_digest": "91d9c1fc-5369-4d62-98dc-9182ecadf7a9",
    "isVerified": true
  },
  {
    "name": "Elise Rau",
    "email": "Mellie32@gmail.com",
    "password_digest": "7975b5bc-a8fa-4b1d-bce2-0197feaf4248",
    "isVerified": true
  },
  {
    "name": "Gust Gibson",
    "email": "Ozella_Luettgen75@yahoo.com",
    "password_digest": "d2815025-64ed-4053-be96-e062fe803676",
    "isVerified": false
  },
  {
    "name": "Mrs. Milo Eichmann",
    "email": "Tia27@gmail.com",
    "password_digest": "a035507c-9811-4a46-bef3-7ee1e67390d3",
    "isVerified": false
  },
  {
    "name": "Cortney Hartmann",
    "email": "Mathias46@hotmail.com",
    "password_digest": "51ee32e6-4c04-4274-93f4-5768883e1cca",
    "isVerified": true
  },
  {
    "name": "Myriam Bartell",
    "email": "Karolann.McClure@hotmail.com",
    "password_digest": "baf8f717-19a0-4739-ac84-a7da78fb762f",
    "isVerified": false
  },
  {
    "name": "Jadon Blick",
    "email": "Emory_Goodwin35@hotmail.com",
    "password_digest": "06d3053c-c1cf-410f-83fa-fd2aa98877e3",
    "isVerified": false
  },
  {
    "name": "Prudence Kuphal IV",
    "email": "Karina53@gmail.com",
    "password_digest": "6dfd2c37-3486-42a6-bf33-87c1869a3c44",
    "isVerified": false
  },
  {
    "name": "Erik Moen DDS",
    "email": "Archibald.Metz14@gmail.com",
    "password_digest": "113ade35-0428-46e9-9a38-ee774253e47c",
    "isVerified": true
  },
  {
    "name": "Theo Veum",
    "email": "Cordell89@hotmail.com",
    "password_digest": "8dc5fac7-175d-4aea-bebc-630ad05ef6b0",
    "isVerified": true
  },
  {
    "name": "Yasmin Smitham",
    "email": "Hoyt_Medhurst64@gmail.com",
    "password_digest": "b83bf12a-4a93-438e-9095-54a0d6a38413",
    "isVerified": false
  },
  {
    "name": "Nicolas Barton",
    "email": "Freeman.Lindgren@yahoo.com",
    "password_digest": "436c4e5e-a99c-4a27-87f9-140ddcddef9e",
    "isVerified": true
  },
  {
    "name": "Victor Ankunding",
    "email": "Betty36@yahoo.com",
    "password_digest": "767cbad4-3eff-48a2-af76-8782d49580dd",
    "isVerified": false
  },
  {
    "name": "Mabel Sawayn",
    "email": "Don66@gmail.com",
    "password_digest": "e9013874-2237-40f9-9020-5ab8a111d035",
    "isVerified": true
  },
  {
    "name": "Cletus Abernathy",
    "email": "Mauricio_Huels35@hotmail.com",
    "password_digest": "0c160910-ed79-4cc3-beb8-6292efbeb342",
    "isVerified": true
  },
  {
    "name": "Miss Francesca Gislason",
    "email": "Brooks_Gleason84@yahoo.com",
    "password_digest": "b316bb42-635e-4265-bbf5-d6edc73d538e",
    "isVerified": false
  },
  {
    "name": "Pedro Lindgren",
    "email": "Hollie73@hotmail.com",
    "password_digest": "82891a60-c01f-4340-95ac-ca85801e6340",
    "isVerified": false
  },
  {
    "name": "Faustino Emard",
    "email": "Rod52@yahoo.com",
    "password_digest": "89b6c0f1-21d9-487c-9e66-56b7c34c54a1",
    "isVerified": false
  },
  {
    "name": "Esperanza Stamm",
    "email": "Carmel_Marquardt2@hotmail.com",
    "password_digest": "a2f7334d-9742-4f44-9f00-dfe6eac076d8",
    "isVerified": true
  },
  {
    "name": "Mr. Payton Paucek",
    "email": "Monte_Runolfsson25@gmail.com",
    "password_digest": "200d07bd-f846-4aaf-b9a1-ccefb25d9083",
    "isVerified": false
  },
  {
    "name": "Jettie O'Connell",
    "email": "Markus5@hotmail.com",
    "password_digest": "c9235b69-046c-4456-87d3-4d5f6e8396be",
    "isVerified": true
  },
  {
    "name": "Katelin Fay Jr.",
    "email": "Alda.Gibson10@yahoo.com",
    "password_digest": "1fa4e144-7747-4607-aebe-a9eabe59cce5",
    "isVerified": false
  },
  {
    "name": "Mrs. Dulce Murray",
    "email": "Kyler.Farrell@gmail.com",
    "password_digest": "e004fd65-3d75-4b9b-ab5e-e6dc5c743b74",
    "isVerified": true
  },
  {
    "name": "Otho Hodkiewicz",
    "email": "Janelle72@yahoo.com",
    "password_digest": "f3c8dd41-82bb-4842-b272-9c5045e846d2",
    "isVerified": true
  },
  {
    "name": "Germaine Smitham",
    "email": "Frederik68@gmail.com",
    "password_digest": "96c2faf2-3cab-437d-bc6c-95fc1fb1d7c2",
    "isVerified": false
  },
  {
    "name": "Myrl Dare MD",
    "email": "Nelda_Satterfield@yahoo.com",
    "password_digest": "ddfc3307-e3c8-473c-9eba-0789b0500265",
    "isVerified": true
  },
  {
    "name": "Eladio Emmerich",
    "email": "Erich.Harris40@yahoo.com",
    "password_digest": "75e64950-cf90-4598-8baa-82f6be3b7b51",
    "isVerified": true
  },
  {
    "name": "Tad Kilback",
    "email": "Alexandrea_Trantow37@gmail.com",
    "password_digest": "8f017160-2900-431d-9171-fa0b163d1fe3",
    "isVerified": true
  },
  {
    "name": "Betsy Koelpin",
    "email": "Barbara.Lehner85@hotmail.com",
    "password_digest": "da854fb4-539a-421e-8bac-7743d7619867",
    "isVerified": true
  },
  {
    "name": "Miss Joshua Koelpin",
    "email": "Reginald_Mosciski84@gmail.com",
    "password_digest": "32fe1f38-ef46-4a4c-8b03-33302acf11e4",
    "isVerified": false
  },
  {
    "name": "Lynn Muller",
    "email": "Ralph.Anderson@hotmail.com",
    "password_digest": "ada0ed28-3529-4f97-9f61-b225d2c22d04",
    "isVerified": true
  },
  {
    "name": "Allie Swift",
    "email": "Jasper.Dibbert@hotmail.com",
    "password_digest": "ba6ccc59-e9e6-47c8-b8e5-5ebd9827fef5",
    "isVerified": true
  },
  {
    "name": "Lewis Terry",
    "email": "Kristofer.Wisozk9@yahoo.com",
    "password_digest": "47fe8179-6a1c-428c-8d97-6250daae8cd3",
    "isVerified": false
  },
  {
    "name": "Mustafa Erdman",
    "email": "Kaylah.Weissnat10@hotmail.com",
    "password_digest": "d9e4b15d-8ddc-4e53-b0dc-0a7fe04c6329",
    "isVerified": false
  },
  {
    "name": "Mrs. Arne Swaniawski",
    "email": "Rosalia_Lehner@hotmail.com",
    "password_digest": "9f8a2ca9-7968-48ef-8cfa-7fb65ed78be5",
    "isVerified": true
  },
  {
    "name": "Miss Daija Johnson",
    "email": "Francis_Yost@yahoo.com",
    "password_digest": "c84ca327-451c-4586-abd9-de2bb7048982",
    "isVerified": true
  },
  {
    "name": "Jewel Ritchie",
    "email": "Aurore.Hauck@yahoo.com",
    "password_digest": "c389342a-7262-4e23-9a6c-066da134d23c",
    "isVerified": true
  },
  {
    "name": "Miss Ruthie Koch",
    "email": "Maximillia92@yahoo.com",
    "password_digest": "38b2c943-e35a-4cb5-9311-2908e2c41e43",
    "isVerified": false
  },
  {
    "name": "Keshaun Rice",
    "email": "Eloise59@hotmail.com",
    "password_digest": "cea21be0-38cc-4711-9454-4314961628ea",
    "isVerified": true
  },
  {
    "name": "Caroline Waters",
    "email": "Manley_Upton38@hotmail.com",
    "password_digest": "196e42e2-2433-4c33-be2f-6e480b33e178",
    "isVerified": false
  },
  {
    "name": "Gayle Grady",
    "email": "Freda19@gmail.com",
    "password_digest": "0b24b661-5097-44f0-b992-c5572a351ec2",
    "isVerified": true
  },
  {
    "name": "Jamar Kling",
    "email": "Emerald_Emmerich@gmail.com",
    "password_digest": "1c626489-17ba-4f74-aef2-1b766ba70439",
    "isVerified": true
  },
  {
    "name": "Nakia O'Conner",
    "email": "Doyle_Hermiston82@gmail.com",
    "password_digest": "ee607f20-e52b-4064-a980-7ddd70b68e42",
    "isVerified": true
  },
  {
    "name": "Celine Jakubowski",
    "email": "Sammy.Metz@gmail.com",
    "password_digest": "3cc37f0c-53d5-40c2-b391-21e28842f512",
    "isVerified": false
  },
  {
    "name": "Jerrod Bergstrom I",
    "email": "Triston21@gmail.com",
    "password_digest": "fb0debfd-c9e7-4341-88b6-268d887ce19b",
    "isVerified": false
  },
  {
    "name": "Carlie McClure",
    "email": "Jordi.Harris@yahoo.com",
    "password_digest": "b56ea8dd-536e-482a-8335-a572bff875b7",
    "isVerified": true
  },
  {
    "name": "Pascale Dietrich",
    "email": "Alberta72@yahoo.com",
    "password_digest": "b7229835-ccb2-4b56-9c8d-5b7569401126",
    "isVerified": true
  },
  {
    "name": "Vince Rosenbaum",
    "email": "Aaliyah.Schiller64@yahoo.com",
    "password_digest": "4ee973e7-2c94-45e4-8ab5-21c443d0d2b9",
    "isVerified": true
  },
  {
    "name": "Jamaal Orn",
    "email": "Emile.Watsica91@hotmail.com",
    "password_digest": "330d90a6-99fe-4594-b97c-026252bc27e0",
    "isVerified": true
  },
  {
    "name": "Matt O'Reilly",
    "email": "Isaiah.Frami96@yahoo.com",
    "password_digest": "18025cc7-49de-4c81-a5ea-02e5f373103d",
    "isVerified": true
  },
  {
    "name": "Rubie Lebsack",
    "email": "Felicity_Krajcik26@gmail.com",
    "password_digest": "601e0cc3-7036-430d-bd4e-46e6034b1a32",
    "isVerified": false
  },
  {
    "name": "Ellie O'Reilly",
    "email": "Coby.Robel97@hotmail.com",
    "password_digest": "36a2875c-ca97-4f4f-a61f-9b31ca4c0d9a",
    "isVerified": false
  },
  {
    "name": "Velma Hudson",
    "email": "Fae_Turner46@yahoo.com",
    "password_digest": "8d8b5e05-5e76-4145-ba57-7f0d6c164ab8",
    "isVerified": false
  },
  {
    "name": "Loy Boyer Sr.",
    "email": "Lawson_Rolfson@gmail.com",
    "password_digest": "37e56fb2-0af2-4a06-b830-055c1d650f84",
    "isVerified": false
  },
  {
    "name": "Jonatan Barton",
    "email": "Garland62@yahoo.com",
    "password_digest": "9ab6c01e-ced7-43e9-be32-dceef4dbf9d9",
    "isVerified": true
  },
  {
    "name": "Cleo Dicki",
    "email": "Aaliyah_Gorczany@yahoo.com",
    "password_digest": "b8827669-0308-4167-a046-9395f43833a4",
    "isVerified": false
  },
  {
    "name": "Pedro Nader",
    "email": "Henri20@yahoo.com",
    "password_digest": "f5433ab0-ffc6-433d-bd21-6c296ad94e43",
    "isVerified": false
  },
  {
    "name": "Doyle Gleichner V",
    "email": "Saul.Marks2@yahoo.com",
    "password_digest": "66330cd2-6cc8-4114-8b78-de39e82eb860",
    "isVerified": true
  },
  {
    "name": "Hillard Pagac I",
    "email": "Noelia18@gmail.com",
    "password_digest": "5964beb7-a10a-4a0d-bea4-90d2c896ce69",
    "isVerified": false
  },
  {
    "name": "Mrs. Lionel Wisoky",
    "email": "Kayla29@hotmail.com",
    "password_digest": "1bcabb4c-8319-4f34-a5e9-6e402f1a8538",
    "isVerified": true
  },
  {
    "name": "Rosalinda Muller",
    "email": "Vance.Casper@gmail.com",
    "password_digest": "997ca65b-f21e-4460-abc8-2c3995d32ffe",
    "isVerified": true
  },
  {
    "name": "Jo Rohan",
    "email": "Maybelle.Bradtke71@gmail.com",
    "password_digest": "f0b090b7-20ad-47f0-a4b2-c19e634ea926",
    "isVerified": true
  },
  {
    "name": "Jaunita Becker",
    "email": "Lew_Sporer@yahoo.com",
    "password_digest": "3c6878bc-0ad9-405a-b631-1a7c408603ff",
    "isVerified": true
  },
  {
    "name": "Della Rath",
    "email": "Tara.Toy@yahoo.com",
    "password_digest": "7061f1b0-e9c1-4810-b460-f0e80bda752b",
    "isVerified": true
  },
  {
    "name": "Tommie Abshire",
    "email": "Victoria30@gmail.com",
    "password_digest": "f4e2c6d0-970e-4409-82ba-28257402e845",
    "isVerified": false
  },
  {
    "name": "Providenci Wunsch",
    "email": "John.Stehr@gmail.com",
    "password_digest": "26940851-8e11-410e-803f-71f12b1eaeb6",
    "isVerified": true
  },
  {
    "name": "Mrs. Bernhard Hills",
    "email": "Chanel.Ruecker7@yahoo.com",
    "password_digest": "bb135020-a86c-4970-b1b3-10508c3d6c69",
    "isVerified": true
  },
  {
    "name": "Mr. Lauriane Jast",
    "email": "Ahmad.Hegmann53@hotmail.com",
    "password_digest": "e5f1a04c-69fc-4979-ad5a-0b7210e318d6",
    "isVerified": true
  },
  {
    "name": "Luisa Hirthe",
    "email": "Amelia_Renner95@hotmail.com",
    "password_digest": "4b5b1da4-aca0-4180-951b-5309c074d6b4",
    "isVerified": true
  },
  {
    "name": "Layla Franecki",
    "email": "Jace.Grady21@hotmail.com",
    "password_digest": "a8ab29d4-2680-4b82-9ebe-193aa17d9883",
    "isVerified": false
  },
  {
    "name": "Dr. Alysa Buckridge",
    "email": "Easter_Hauck0@hotmail.com",
    "password_digest": "fe6ccaa4-3850-4d13-b1c5-03a7833827ff",
    "isVerified": true
  },
  {
    "name": "Adela Friesen Jr.",
    "email": "Rowena.Bogisich@gmail.com",
    "password_digest": "6a31f949-d03a-4803-b751-1cb001eb2a48",
    "isVerified": false
  },
  {
    "name": "Ella Stanton",
    "email": "Nya_Kling56@yahoo.com",
    "password_digest": "0ddcbed8-d9c5-4daf-beca-cc3b245c769d",
    "isVerified": false
  },
  {
    "name": "Justen Kreiger DVM",
    "email": "Darrin_Erdman@hotmail.com",
    "password_digest": "0f8aeae8-55b3-467c-b9a3-52eb75a0818a",
    "isVerified": true
  },
  {
    "name": "Isabelle Hirthe",
    "email": "Tania.Schimmel56@gmail.com",
    "password_digest": "944297d7-1c20-4ab4-8579-f9b383caf93a",
    "isVerified": true
  },
  {
    "name": "Jeanie Schmitt",
    "email": "Maximillian21@hotmail.com",
    "password_digest": "44d7e588-1b71-4771-9746-728e65a281ae",
    "isVerified": true
  },
  {
    "name": "Darrell Cassin",
    "email": "Lucius.Bergstrom@gmail.com",
    "password_digest": "d799c01d-564b-4ba1-99ad-28f5839d546b",
    "isVerified": true
  },
  {
    "name": "Geovanny Tremblay MD",
    "email": "Alverta.Kihn@gmail.com",
    "password_digest": "e6ae44a6-663e-4368-b114-a7cf16eb595f",
    "isVerified": true
  },
  {
    "name": "Nakia Wilkinson",
    "email": "Bette35@hotmail.com",
    "password_digest": "d45aa685-70f3-4bc7-8864-bf8adb0b00eb",
    "isVerified": true
  },
  {
    "name": "Waylon Roberts PhD",
    "email": "Eve_Stokes@gmail.com",
    "password_digest": "746fbea2-a565-4a7e-81dc-0d48e0f8223c",
    "isVerified": true
  },
  {
    "name": "Dulce Jaskolski",
    "email": "Lauretta.King13@yahoo.com",
    "password_digest": "fbf555a3-5b15-4175-9b29-6776b2c4b715",
    "isVerified": true
  },
  {
    "name": "Cassidy Gleichner",
    "email": "Craig11@gmail.com",
    "password_digest": "756ec5ca-dbaf-4902-819d-10cfdeb373c2",
    "isVerified": true
  },
  {
    "name": "Aubrey Champlin DVM",
    "email": "Keaton_Schuster@gmail.com",
    "password_digest": "579b9027-9af2-4272-8dab-d2de6c0d013f",
    "isVerified": true
  },
  {
    "name": "Eda Schroeder III",
    "email": "Emelia.Spencer@yahoo.com",
    "password_digest": "40cc5afa-2fdc-4b5f-88f2-02330e13947d",
    "isVerified": false
  },
  {
    "name": "Mary Hansen",
    "email": "Albina32@yahoo.com",
    "password_digest": "90ffb5cc-1a03-4159-a1ea-c648ca819fe2",
    "isVerified": true
  },
  {
    "name": "Lester Fay",
    "email": "Cornell3@gmail.com",
    "password_digest": "c4900421-fceb-4fd8-a173-2978aa13f0d5",
    "isVerified": true
  },
  {
    "name": "Antwan Kessler",
    "email": "Deborah_Kassulke9@gmail.com",
    "password_digest": "13e2cb42-7c97-4666-8607-43e414c872d3",
    "isVerified": false
  },
  {
    "name": "Shakira Botsford",
    "email": "Mathew2@gmail.com",
    "password_digest": "c332c59e-35de-4dc4-bbdb-ce7a2b3d6b07",
    "isVerified": true
  },
  {
    "name": "Mellie Wisozk",
    "email": "Eloisa.Satterfield@gmail.com",
    "password_digest": "217accd9-42ea-45da-8c20-9827d198522a",
    "isVerified": false
  },
  {
    "name": "Elroy Satterfield",
    "email": "Patrick99@gmail.com",
    "password_digest": "e5905a4a-19e4-4a6d-a9d8-1b42459638a7",
    "isVerified": true
  },
  {
    "name": "Ollie Ondricka",
    "email": "Benton.Kerluke@yahoo.com",
    "password_digest": "2c50b419-448f-425f-94bc-2f2dba7da77c",
    "isVerified": false
  },
  {
    "name": "Mrs. Turner Homenick",
    "email": "Rosemary_Huels52@gmail.com",
    "password_digest": "8e7352d8-0a05-4bdc-b7e2-08f4df40e697",
    "isVerified": false
  },
  {
    "name": "Gail Zboncak",
    "email": "Tavares14@gmail.com",
    "password_digest": "4c381c61-47d4-456d-a4eb-a2f4a77960de",
    "isVerified": true
  },
  {
    "name": "Margie Gibson PhD",
    "email": "Danika18@yahoo.com",
    "password_digest": "4763b536-c939-41b2-8adc-b9680ada3ccb",
    "isVerified": true
  },
  {
    "name": "Buddy Hessel",
    "email": "Nikko.Steuber@yahoo.com",
    "password_digest": "0d882cbf-fa1c-488f-a6c8-1c49a27c8280",
    "isVerified": true
  },
  {
    "name": "Verner Schuster",
    "email": "Jaron.Lang@gmail.com",
    "password_digest": "a616614d-147a-4085-8f5b-2b13e98a39ad",
    "isVerified": false
  },
  {
    "name": "Gilda White",
    "email": "Kayla_Corwin4@gmail.com",
    "password_digest": "58dc4e2b-0abb-440c-828a-4e9f3da9d8a0",
    "isVerified": false
  },
  {
    "name": "Alec Altenwerth",
    "email": "Vena_Ruecker68@gmail.com",
    "password_digest": "c1b06146-abcb-43c9-b201-45d5fa9584fe",
    "isVerified": false
  },
  {
    "name": "Nathanael Spencer",
    "email": "Vidal.Kautzer7@hotmail.com",
    "password_digest": "8f0aa2b6-3529-45da-b08e-f030a2b65739",
    "isVerified": true
  },
  {
    "name": "Allene Bartell IV",
    "email": "Sydni_Goyette84@gmail.com",
    "password_digest": "dcd0daf3-1af3-4b68-8505-f37ff75800f7",
    "isVerified": true
  },
  {
    "name": "Daphney Kilback MD",
    "email": "Tavares39@gmail.com",
    "password_digest": "bf410ee0-426f-4d11-8a85-620eee225d09",
    "isVerified": false
  },
  {
    "name": "Emmitt Kiehn",
    "email": "Nicola67@hotmail.com",
    "password_digest": "288cff52-ba59-4065-a009-652c7256f161",
    "isVerified": false
  },
  {
    "name": "Kenton Cassin",
    "email": "Jaydon_Treutel@hotmail.com",
    "password_digest": "111a1d87-afdc-4197-a1a2-ede430982fa6",
    "isVerified": true
  },
  {
    "name": "Stephan Kihn",
    "email": "Heath_Feil@gmail.com",
    "password_digest": "f89d98cb-870f-4368-92d3-d4c71f6ea588",
    "isVerified": false
  },
  {
    "name": "Lennie Runte MD",
    "email": "Joel.Renner72@hotmail.com",
    "password_digest": "7f95bef9-2aaf-4fd8-9470-07b83fc280d5",
    "isVerified": true
  },
  {
    "name": "Remington Gusikowski",
    "email": "Beulah85@hotmail.com",
    "password_digest": "17b61684-dd0a-4687-8b32-f2ecba83a860",
    "isVerified": true
  },
  {
    "name": "Mrs. Cleta Champlin",
    "email": "Janelle_Rosenbaum@yahoo.com",
    "password_digest": "4f911598-2955-4a1a-86a6-4d04eadd188d",
    "isVerified": true
  },
  {
    "name": "Mrs. Eli Friesen",
    "email": "Stefan_Runte10@yahoo.com",
    "password_digest": "8ef5c6e3-af65-4e28-b881-0c1b3426b3e6",
    "isVerified": false
  },
  {
    "name": "Bertram Labadie V",
    "email": "Amber.Muller31@hotmail.com",
    "password_digest": "f64d3dca-0764-449e-bf62-ccb2a51d6ca8",
    "isVerified": true
  },
  {
    "name": "Mrs. Brandy Waters",
    "email": "Alexane.Reilly@hotmail.com",
    "password_digest": "fda5ee79-43db-4018-b185-92a22a4fc4d5",
    "isVerified": false
  },
  {
    "name": "Kaycee Konopelski",
    "email": "Haley5@yahoo.com",
    "password_digest": "29da7f3a-03bc-4e58-92e6-5511ec6a17ff",
    "isVerified": true
  },
  {
    "name": "Neha Hyatt",
    "email": "Angie14@gmail.com",
    "password_digest": "5fb5249a-cf33-4fde-a75f-aa14b3f43a76",
    "isVerified": true
  },
  {
    "name": "Joany Goodwin",
    "email": "Alan33@gmail.com",
    "password_digest": "996aff5c-8a49-40d5-ac5b-dbb6bc203d37",
    "isVerified": true
  },
  {
    "name": "Alfreda Moore",
    "email": "Lily34@yahoo.com",
    "password_digest": "853fbc89-ce9e-4305-b42a-b136d598b892",
    "isVerified": false
  },
  {
    "name": "Abigail Ruecker",
    "email": "Julius_Hane@yahoo.com",
    "password_digest": "34214054-af7c-4e77-b2f8-b0057c28c0fd",
    "isVerified": true
  },
  {
    "name": "Nels Labadie",
    "email": "Brielle.Roob@hotmail.com",
    "password_digest": "0150e4f9-7431-4390-9439-39460d2ebcfa",
    "isVerified": false
  },
  {
    "name": "Maria Swift",
    "email": "Shany39@yahoo.com",
    "password_digest": "b391931a-1ae6-483c-9acb-94f1d1e98a6f",
    "isVerified": true
  },
  {
    "name": "Dante Murray",
    "email": "Nolan79@yahoo.com",
    "password_digest": "3ad0b64b-b645-4a61-8bb6-284510a93194",
    "isVerified": false
  },
  {
    "name": "Dr. Katrine Brown",
    "email": "Jazmin.Davis74@gmail.com",
    "password_digest": "4ce6e672-e944-467a-a0d3-c5fd174c9dad",
    "isVerified": true
  },
  {
    "name": "Wendy Considine",
    "email": "Emery_Rempel@hotmail.com",
    "password_digest": "f5d7abeb-cd8c-4001-9f46-e26e96a657ac",
    "isVerified": false
  },
  {
    "name": "Fausto Dare",
    "email": "Arno.Kunze@yahoo.com",
    "password_digest": "d7f3bbe1-981b-45ff-be2c-79787fbdd9be",
    "isVerified": false
  },
  {
    "name": "Dr. Omari Kulas",
    "email": "Marilie.Schoen@gmail.com",
    "password_digest": "1f665d70-4eac-4ca7-bc84-022facfbcad3",
    "isVerified": false
  },
  {
    "name": "Miss Willie Bergstrom",
    "email": "Aaliyah17@gmail.com",
    "password_digest": "dd4e06b0-3e22-4450-a367-dc9b117f202e",
    "isVerified": true
  },
  {
    "name": "Mrs. Constance Stracke",
    "email": "Ian_West@gmail.com",
    "password_digest": "b7adbb34-08bf-4217-9157-b06e89b72605",
    "isVerified": false
  },
  {
    "name": "Lilly Mertz",
    "email": "Larissa60@yahoo.com",
    "password_digest": "e88241e0-d7b6-4cea-bac8-450f89ad6fa2",
    "isVerified": false
  },
  {
    "name": "Dawson Lakin",
    "email": "Nasir_Schimmel@gmail.com",
    "password_digest": "a1a31759-08f5-4ad1-8ebb-55b541ea6c80",
    "isVerified": false
  },
  {
    "name": "Gwen Bergnaum",
    "email": "Raegan20@hotmail.com",
    "password_digest": "3780e935-28cb-4ba4-a033-3f58e375b7ab",
    "isVerified": true
  },
  {
    "name": "Major Shields MD",
    "email": "Modesta_Daniel@yahoo.com",
    "password_digest": "97fd43c7-da31-4e57-ba52-e2ea81c6f44e",
    "isVerified": false
  },
  {
    "name": "Austin Hand IV",
    "email": "Glenda_Kozey59@gmail.com",
    "password_digest": "cc9bccf6-a76a-4eab-a4eb-8b07b26dca5c",
    "isVerified": false
  },
  {
    "name": "Dr. Kole Hane",
    "email": "Natalie_Yost@gmail.com",
    "password_digest": "a2a0de26-8b14-4898-8f08-63330c6928dd",
    "isVerified": false
  },
  {
    "name": "Brooklyn Brakus",
    "email": "Jessika.Nicolas74@gmail.com",
    "password_digest": "4535ff28-dd31-47f9-8b31-dcb0cd00827e",
    "isVerified": false
  },
  {
    "name": "Arjun Orn",
    "email": "Colin_Conn@yahoo.com",
    "password_digest": "d84e001a-3983-4f59-a572-ff2a290dc4d3",
    "isVerified": false
  },
  {
    "name": "Dr. Garret Leannon",
    "email": "Madelynn_Daugherty71@yahoo.com",
    "password_digest": "8fce274b-c1ea-4238-8e00-e5edcd8820da",
    "isVerified": true
  },
  {
    "name": "Myah Runolfsdottir",
    "email": "Cydney66@yahoo.com",
    "password_digest": "4db71d2c-d083-4f34-9259-3c74bb6cb53b",
    "isVerified": false
  },
  {
    "name": "Celine Kuvalis",
    "email": "Lavonne28@gmail.com",
    "password_digest": "8b486d6c-4300-42bb-a144-3b7f6b9eebb6",
    "isVerified": true
  },
  {
    "name": "Santos Doyle",
    "email": "Luella_Mitchell74@gmail.com",
    "password_digest": "7f58210c-1c39-49f0-bd19-5b80e1056b19",
    "isVerified": true
  },
  {
    "name": "Curt Bradtke",
    "email": "Santa_Kozey@yahoo.com",
    "password_digest": "4f0814e9-1f44-407f-80ab-2a205b5909d2",
    "isVerified": false
  },
  {
    "name": "Enrico Feeney",
    "email": "Davion_Durgan37@yahoo.com",
    "password_digest": "d777e8db-01cb-4131-9c09-c7e8241bd359",
    "isVerified": true
  },
  {
    "name": "Stephanie Adams",
    "email": "Joesph.Pagac73@yahoo.com",
    "password_digest": "5b1943d5-5f34-4dae-9dba-af9ae3dc3135",
    "isVerified": false
  },
  {
    "name": "Lindsay Kihn",
    "email": "Alicia.Block@hotmail.com",
    "password_digest": "2ce96f8a-5e28-4130-ad76-23f13781f02f",
    "isVerified": false
  },
  {
    "name": "Kyra Kunde II",
    "email": "Eldred.Runolfsson@gmail.com",
    "password_digest": "839439ae-bfff-4a7e-84d8-5d939ed866d5",
    "isVerified": false
  },
  {
    "name": "Schuyler Gorczany",
    "email": "Kameron.Keeling@hotmail.com",
    "password_digest": "b6337f1a-77a9-4daf-82ad-07df6d8f4d00",
    "isVerified": false
  },
  {
    "name": "Kobe Turner",
    "email": "Tristian.Padberg83@yahoo.com",
    "password_digest": "39e6b8c4-4bfc-4385-80df-763c5e9fe894",
    "isVerified": false
  },
  {
    "name": "Ericka Ankunding I",
    "email": "Cristobal_Kertzmann@hotmail.com",
    "password_digest": "dbe8f8f4-0848-4731-a68e-31abcfb05382",
    "isVerified": true
  },
  {
    "name": "Darby Willms",
    "email": "Willis64@hotmail.com",
    "password_digest": "63cac712-0074-4a01-a53c-4cdffad0bb2f",
    "isVerified": false
  },
  {
    "name": "Miguel Runolfsson",
    "email": "Norene_Gutkowski46@yahoo.com",
    "password_digest": "83157a4b-0e83-4810-9952-e3fed31b23fc",
    "isVerified": true
  },
  {
    "name": "Mellie Wuckert",
    "email": "Arely_Abernathy@hotmail.com",
    "password_digest": "d29ee537-4573-4f48-a802-e1a2ed32a889",
    "isVerified": false
  },
  {
    "name": "Prudence Kertzmann",
    "email": "Arden40@hotmail.com",
    "password_digest": "553fb166-4d1c-459d-bd79-bcf33883d700",
    "isVerified": true
  },
  {
    "name": "Celine Kozey",
    "email": "Jaclyn.Kautzer@hotmail.com",
    "password_digest": "b3ecadc2-910f-4e74-99ee-d2381842a5c8",
    "isVerified": true
  },
  {
    "name": "Alanis Johnston",
    "email": "Emmanuel65@hotmail.com",
    "password_digest": "9233c0ed-04df-405a-b113-749745250331",
    "isVerified": false
  },
  {
    "name": "Otto Gutmann",
    "email": "Jovan.Olson88@gmail.com",
    "password_digest": "da8540f7-ffc9-481b-9708-fff4586f6b18",
    "isVerified": false
  },
  {
    "name": "Jasmin Sporer",
    "email": "Amalia59@hotmail.com",
    "password_digest": "69c7ee71-34de-4c2c-809a-c12f2971bf24",
    "isVerified": false
  },
  {
    "name": "Beverly Beahan",
    "email": "Odessa2@yahoo.com",
    "password_digest": "4b3a3975-0aa8-4644-9b9b-2c7fe9abbdf8",
    "isVerified": true
  },
  {
    "name": "Ervin Johnson",
    "email": "Serenity_Hauck@gmail.com",
    "password_digest": "02944d0d-5d0a-4490-8d3c-91278d510806",
    "isVerified": true
  },
  {
    "name": "Aaron Will",
    "email": "Makayla59@yahoo.com",
    "password_digest": "f4ee391b-7f0e-4981-a93e-ef5ed43ec6dd",
    "isVerified": true
  },
  {
    "name": "Dr. Adah Hand",
    "email": "Bertram.Hahn9@gmail.com",
    "password_digest": "2e17508a-f3f9-4fd8-98d8-ebcea28e5183",
    "isVerified": true
  },
  {
    "name": "Bennie Trantow",
    "email": "Maybell_Emmerich@gmail.com",
    "password_digest": "b21772c2-f1d3-455e-b0df-e752e7e7f672",
    "isVerified": false
  },
  {
    "name": "Dr. Gunner Bayer",
    "email": "Florine36@yahoo.com",
    "password_digest": "53bf0382-60df-45de-a934-00bd727a1921",
    "isVerified": true
  },
  {
    "name": "Mrs. Enola Crooks",
    "email": "Mathias_Rath@hotmail.com",
    "password_digest": "15534491-f1a7-465f-8dea-be46fc11077a",
    "isVerified": true
  },
  {
    "name": "Effie Spencer",
    "email": "Guiseppe30@gmail.com",
    "password_digest": "89902114-19dc-4808-819b-0f4c4b3f576d",
    "isVerified": false
  },
  {
    "name": "Carolyn Crist",
    "email": "Dorcas15@hotmail.com",
    "password_digest": "89f63418-0e44-40d2-adef-7b3f830e2327",
    "isVerified": true
  },
  {
    "name": "Zena Will",
    "email": "Zetta90@yahoo.com",
    "password_digest": "5d5e9d94-6bab-4e95-9f41-b5ef641c1193",
    "isVerified": true
  },
  {
    "name": "Bettye Mraz",
    "email": "June17@gmail.com",
    "password_digest": "eb4e1863-8d8f-46b0-a98d-d2c6df57c29c",
    "isVerified": true
  },
  {
    "name": "Louie Corwin",
    "email": "Joelle9@gmail.com",
    "password_digest": "300a193f-9b1a-4567-b759-c8701db6ffeb",
    "isVerified": true
  },
  {
    "name": "Israel Hudson",
    "email": "Bridget86@yahoo.com",
    "password_digest": "4d556ea8-9bf0-4a92-bef7-17ed2fff7fd2",
    "isVerified": false
  },
  {
    "name": "Shania Zulauf",
    "email": "Betty_Watsica@yahoo.com",
    "password_digest": "8c50e635-705a-48db-8469-fa51760dced6",
    "isVerified": false
  },
  {
    "name": "Madelyn Carroll",
    "email": "Marlene.Douglas73@gmail.com",
    "password_digest": "1e40ca4b-cc96-46f6-9942-b4fa07af8eff",
    "isVerified": true
  },
  {
    "name": "Ole Jones",
    "email": "Louie.Yost95@hotmail.com",
    "password_digest": "258e4bf4-d410-49dc-a4dc-5415a8d96f66",
    "isVerified": false
  },
  {
    "name": "Rosamond Fritsch",
    "email": "Sarina53@hotmail.com",
    "password_digest": "7965ed10-d8cc-4424-915d-3974ae77e00e",
    "isVerified": false
  },
  {
    "name": "Brandon Wisoky",
    "email": "Zola.Ondricka@yahoo.com",
    "password_digest": "a5dfc2b8-de34-402c-86e5-947fbdcf4d14",
    "isVerified": false
  },
  {
    "name": "Charlotte Sporer",
    "email": "Jamal.Gorczany52@hotmail.com",
    "password_digest": "870e99f8-6ee3-457f-af6a-f4a13f371032",
    "isVerified": true
  },
  {
    "name": "Alta Dibbert",
    "email": "Angie.Haley69@yahoo.com",
    "password_digest": "95692945-73c8-4be2-9b2c-9b91c03a0d74",
    "isVerified": true
  },
  {
    "name": "Ashlee Bogisich",
    "email": "Reuben.Weber@yahoo.com",
    "password_digest": "b3dba096-4260-4259-94c2-9fd6d564e72c",
    "isVerified": true
  },
  {
    "name": "Kyler Jakubowski",
    "email": "Mckenna54@hotmail.com",
    "password_digest": "0382b26c-51d8-490c-82a0-cb5be6683323",
    "isVerified": true
  },
  {
    "name": "Marjory Kris",
    "email": "Stephan_Carter97@gmail.com",
    "password_digest": "55171714-b93a-4549-bede-bef92da6b91f",
    "isVerified": false
  },
  {
    "name": "Elinore Weissnat",
    "email": "Eva.Haley52@yahoo.com",
    "password_digest": "9f883532-cf81-41b1-8cb1-0e43c32bf6d5",
    "isVerified": true
  },
  {
    "name": "Makenna Mante",
    "email": "Leann.Schneider19@yahoo.com",
    "password_digest": "d3327a8e-990d-4613-8f44-d6591c2d4fdc",
    "isVerified": true
  },
  {
    "name": "Jesse Abbott",
    "email": "Bridgette38@yahoo.com",
    "password_digest": "5400999f-9766-47ba-9e5c-4cc1c74425e0",
    "isVerified": false
  },
  {
    "name": "Miss Skyla Turcotte",
    "email": "Jarrod32@gmail.com",
    "password_digest": "486e42aa-7c30-4df9-83f9-c0447df3bfe2",
    "isVerified": false
  },
  {
    "name": "Wendy Wiegand",
    "email": "Shirley86@hotmail.com",
    "password_digest": "c64888ab-684d-4a2f-a787-be158968f845",
    "isVerified": false
  },
  {
    "name": "Lincoln McClure",
    "email": "Grayson_Larkin51@yahoo.com",
    "password_digest": "c8a92779-3f00-4ba9-a409-e5bfca84e844",
    "isVerified": true
  },
  {
    "name": "Floy Marvin",
    "email": "Brandon_Zulauf@gmail.com",
    "password_digest": "0e8ad981-d36a-4902-b077-b3023f0747ab",
    "isVerified": true
  },
  {
    "name": "Crawford Lindgren",
    "email": "Patricia_Jacobson@yahoo.com",
    "password_digest": "6674b1e9-32f5-4c2e-9bb7-65425b564495",
    "isVerified": true
  },
  {
    "name": "Reilly Becker",
    "email": "Agustin.Hettinger@gmail.com",
    "password_digest": "96caccbd-355b-4261-bc71-d664aed3ad02",
    "isVerified": true
  },
  {
    "name": "Nella Ortiz",
    "email": "Leilani.Bailey47@gmail.com",
    "password_digest": "5fededf1-eb5b-4610-b2ac-b62a1b61942b",
    "isVerified": true
  },
  {
    "name": "Lilly Rippin",
    "email": "Lonzo.Stroman3@yahoo.com",
    "password_digest": "bb3a72ff-0536-4db3-93f3-24801f246c0f",
    "isVerified": true
  },
  {
    "name": "Calista Kulas",
    "email": "Candice34@yahoo.com",
    "password_digest": "20d8f472-e390-436d-a9f9-50b45cd08184",
    "isVerified": true
  },
  {
    "name": "Kenny Schmitt",
    "email": "Max65@gmail.com",
    "password_digest": "3317158d-e2a2-41c5-bf65-8b2284502981",
    "isVerified": false
  },
  {
    "name": "Magnus Donnelly",
    "email": "Camila_Macejkovic59@yahoo.com",
    "password_digest": "bcf97081-d181-472e-9519-200cb760bd9f",
    "isVerified": true
  },
  {
    "name": "Lura Botsford",
    "email": "Sid_Spencer56@hotmail.com",
    "password_digest": "3ff97cff-ddbb-4e9f-b31b-7fd6aef9ac48",
    "isVerified": true
  },
  {
    "name": "Jaron Emmerich",
    "email": "Halie98@yahoo.com",
    "password_digest": "e0a9ebd6-679a-41ee-a4ca-33b8e1908f3b",
    "isVerified": true
  },
  {
    "name": "Paula Balistreri",
    "email": "Gabe48@gmail.com",
    "password_digest": "e084fa75-dc73-4fcb-a820-6a07cb0252d3",
    "isVerified": false
  },
  {
    "name": "Margarette Franecki",
    "email": "Garland57@yahoo.com",
    "password_digest": "7adeacb5-6250-47fb-90be-5c1116280a4f",
    "isVerified": true
  },
  {
    "name": "Liana Medhurst",
    "email": "Rodger31@hotmail.com",
    "password_digest": "e32f0050-2ae3-466f-855d-d8ff14e1e8ed",
    "isVerified": true
  },
  {
    "name": "Dr. Murphy O'Hara",
    "email": "Wilfrid63@yahoo.com",
    "password_digest": "8896d00b-d211-4838-9a40-141e1243608d",
    "isVerified": true
  },
  {
    "name": "Cyril Crooks",
    "email": "Ruby94@hotmail.com",
    "password_digest": "eb8a0b55-f760-46aa-9b54-cfc32f12901b",
    "isVerified": true
  },
  {
    "name": "Jimmy Langworth",
    "email": "Anastacio_Schroeder@hotmail.com",
    "password_digest": "8e227188-aefc-41a3-a610-4f93c5f637bc",
    "isVerified": true
  },
  {
    "name": "Hobart Greenholt",
    "email": "Eliseo_Purdy11@gmail.com",
    "password_digest": "a3d34240-1162-4567-80cf-7c84289c4ed4",
    "isVerified": false
  },
  {
    "name": "Elise Huels",
    "email": "Pablo_Thompson@yahoo.com",
    "password_digest": "44605cb4-294b-48cc-a3ef-95e6faba3fa2",
    "isVerified": true
  },
  {
    "name": "Pauline Dibbert",
    "email": "Xavier_Ernser@gmail.com",
    "password_digest": "de822de9-5269-4abf-9472-2887a95b48ea",
    "isVerified": true
  },
  {
    "name": "Leif Eichmann",
    "email": "Ryan.Ruecker@hotmail.com",
    "password_digest": "fdbbf249-e61b-40b7-add8-0d529b8efe4b",
    "isVerified": true
  },
  {
    "name": "Kali Kerluke",
    "email": "Darryl.Kreiger@yahoo.com",
    "password_digest": "9a99a97d-81fb-4eb6-af76-8d131300bb47",
    "isVerified": true
  }
]